attendance_tool_msp/__init__.py
attendance_tool_msp/argument_parser.py
attendance_tool_msp/exporter.py
attendance_tool_msp/gui/__init__.py
attendance_tool_msp/gui/assets/app_icon.ico
attendance_tool_msp/gui/assets/msp_logo.png
attendance_tool_msp/gui/assets/pdf_icon.png
attendance_tool_msp/gui/assets/upload_icon.png
attendance_tool_msp/gui/assets/word_icon.png
attendance_tool_msp/gui/gui.py
attendance_tool_msp/processor.py
attendance_tool_msp-1.0.3.dist-info/WHEEL
attendance_tool_msp-1.0.3.dist-info/METADATA
attendance_tool_msp-1.0.3.dist-info/RECORD
