Metadata-Version: 2.4
Name: attendance-tool-msp
Version: 1.0.3
Summary: Automated attendance processing and reporting tool for MSP technical sessions.
Author: mohamedelziat50
Author-email: mohamedelziat50 <mohamedelziat50@gmail.com>
License-Expression: MIT
Requires-Dist: python-docx
Requires-Dist: docx2pdf
Requires-Dist: validators
Requires-Dist: customtkinter
Requires-Dist: pillow
Requires-Python: >=3.10
Project-URL: Documentation, https://attendance-automation-msp.readthedocs.io/
Project-URL: Repository, https://github.com/mohamedelziat50/attendance-automation-MSP
